[
	{
		"id": "cn-qingdao",
		"local_name": "华北 1",
		"ots_instance_types": [
			"HYBRID"
		],
		"region_id": "cn-qingdao"
	},
	{
		"id": "cn-beijing",
		"local_name": "华北 2",
		"ots_instance_types": [
			"HYBRID"
		],
		"region_id": "cn-beijing"
	},
	{
		"id": "cn-zhangjiakou",
		"local_name": "华北 3",
		"ots_instance_types": [
			"HYBRID"
		],
		"region_id": "cn-zhangjiakou"
	},
	{
		"id": "cn-huhehaote",
		"local_name": "华北 5",
		"ots_instance_types": [
			"HYBRID"
		],
		"region_id": "cn-huhehaote"
	},
	{
		"id": "cn-hangzhou",
		"local_name": "华东 1",
		"ots_instance_types": [
			"HYBRID"
		],
		"region_id": "cn-hangzhou"
	},
	{
		"id": "cn-shanghai",
		"local_name": "华东 2",
		"ots_instance_types": [
			"HYBRID"
		],
		"region_id": "cn-shanghai"
	},
	{
		"id": "cn-shenzhen",
		"local_name": "华南 1",
		"ots_instance_types": [
			"HYBRID"
		],
		"region_id": "cn-shenzhen"
	},
	{
		"id": "cn-hongkong",
		"local_name": "香港",
		"ots_instance_types": [
			"HYBRID"
		],
		"region_id": "cn-hongkong"
	},
	{
		"id": "ap-northeast-1",
		"local_name": "亚太东北 1 (东京)",
		"ots_instance_types": [
			"HYBRID"
		],
		"region_id": "ap-northeast-1"
	},
	{
		"id": "ap-southeast-1",
		"local_name": "亚太东南 1 (新加坡)",
		"ots_instance_types": [
			"HYBRID"
		],
		"region_id": "ap-southeast-1"
	},
	{
		"id": "ap-southeast-2",
		"local_name": "亚太东南 2 (悉尼)",
		"ots_instance_types": [
			"HYBRID"
		],
		"region_id": "ap-southeast-2"
	},
	{
		"id": "ap-southeast-3",
		"local_name": "亚太东南 3 (吉隆坡)",
		"ots_instance_types": [
			"HYBRID"
		],
		"region_id": "ap-southeast-3"
	},
	{
		"id": "ap-southeast-5",
		"local_name": "亚太东南 5 (雅加达)",
		"ots_instance_types": [
			"HYBRID"
		],
		"region_id": "ap-southeast-5"
	},
	{
		"id": "ap-south-1",
		"local_name": "亚太南部 1 (孟买)",
		"ots_instance_types": [
			"HYBRID"
		],
		"region_id": "ap-south-1"
	},
	{
		"id": "us-east-1",
		"local_name": "美国东部 1 (弗吉尼亚)",
		"ots_instance_types": [
			"HYBRID"
		],
		"region_id": "us-east-1"
	},
	{
		"id": "us-west-1",
		"local_name": "美国西部 1 (硅谷)",
		"ots_instance_types": [
			"HYBRID"
		],
		"region_id": "us-west-1"
	},
	{
		"id": "eu-west-1",
		"local_name": "英国 (伦敦)",
		"ots_instance_types": [
			"HYBRID"
		],
		"region_id": "eu-west-1"
	},
	{
		"id": "me-east-1",
		"local_name": "中东东部 1 (迪拜)",
		"ots_instance_types": [
			"HYBRID"
		],
		"region_id": "me-east-1"
	},
	{
		"id": "eu-central-1",
		"local_name": "欧洲中部 1 (法兰克福)",
		"ots_instance_types": [
			"HYBRID"
		],
		"region_id": "eu-central-1"
	}
]